streamlit_sql/__init__.py
streamlit_sql/create_delete_model.py
streamlit_sql/filters.py
streamlit_sql/input_fields.py
streamlit_sql/lib.py
streamlit_sql/many.py
streamlit_sql/params.py
streamlit_sql/read_cte.py
streamlit_sql/sql_iu.py
streamlit_sql/update_model.py
streamlit_sql-0.3.2.dist-info/METADATA
streamlit_sql-0.3.2.dist-info/WHEEL
streamlit_sql-0.3.2.dist-info/top_level.txt
streamlit_sql-0.3.2.dist-info/RECORD
