Metadata-Version: 2.4
Name: streamlit_sql
Version: 0.3.2
Summary: CRUD interface for sqlalchemy using streamlit
License: MIT License
Project-URL: homepage, https://github.com/edkedk99/streamlit_sql
Project-URL: documentation, https://edkedk99.github.io/streamlit_sql/
Project-URL: repository, https://github.com/edkedk99/streamlit_sql
Requires-Python: >=3.13
Requires-Dist: python-dateutil
Requires-Dist: pandas
Requires-Dist: sqlalchemy
Requires-Dist: streamlit
Requires-Dist: streamlit_datalist
Requires-Dist: streamlit_antd_components
Requires-Dist: loguru>=0.7.3
